MANIFEST.in
README.rst
setup.py
extended_sitemap/__init__.py
extended_sitemap/sitemap-stylesheet.xsl
extended_sitemap/tests/__init__.py
extended_sitemap/tests/content/articles/article1.md
extended_sitemap/tests/content/articles/article2.md
extended_sitemap/tests/content/articles/article3.md
extended_sitemap/tests/content/pages/page1.md
extended_sitemap/tests/content/pages/page2.md
extended_sitemap/tests/content/pages/page3.md
extended_sitemap/tests/content/pages/page4.md
extended_sitemap/tests/expected/test_sitemap_structure.xml
extended_sitemap/tests/expected/test_sitemap_structure_custom_article_url.xml
extended_sitemap/tests/expected/test_sitemap_structure_direct_templates_1.xml
extended_sitemap/tests/expected/test_sitemap_structure_direct_templates_2.xml
extended_sitemap/tests/expected/test_sitemap_structure_subpath.xml
pelican_extended_sitemap.egg-info/PKG-INFO
pelican_extended_sitemap.egg-info/SOURCES.txt
pelican_extended_sitemap.egg-info/dependency_links.txt
pelican_extended_sitemap.egg-info/top_level.txt