Metadata-Version: 1.1
Name: pelican-extended-sitemap
Version: 1.2.3
Summary: sitemap generator plugin for pelican
Home-page: https://github.com/dArignac/pelican-extended-sitemap
Author: Alexander Herrmann
Author-email: darignac@gmail.com
License: MIT
Platform: UNKNOWN
Classifier: Development Status :: 5 - Production/Stable
Classifier: Environment :: Console
Classifier: Intended Audience :: Developers
Classifier: License :: OSI Approved :: MIT License
Classifier: Natural Language :: English
Classifier: Operating System :: POSIX :: Linux
Classifier: Programming Language :: Python
Classifier: Programming Language :: Python :: 2.7
Classifier: Programming Language :: Python :: 3.4
Classifier: Programming Language :: Python :: 3.5
Classifier: Programming Language :: Python :: 3.6
Classifier: Topic :: Text Processing :: Markup
Requires: pelican
